LICENSE
MANIFEST.in
README.md
setup.py
fancy_cache/__init__.py
fancy_cache/cache_page.py
fancy_cache/middleware.py
fancy_cache.egg-info/PKG-INFO
fancy_cache.egg-info/SOURCES.txt
fancy_cache.egg-info/dependency_links.txt
fancy_cache.egg-info/not-zip-safe
fancy_cache.egg-info/top_level.txt
fancy_cache/tests/__init__.py
fancy_cache/tests/models.py
fancy_cache/tests/settings.py
fancy_cache/tests/test_views.py
fancy_cache/tests/urls.py
fancy_cache/tests/views.py