Metadata-Version: 1.0
Name: fancy-cache
Version: 0.1
Summary: clears the junk out of your CSS
Home-page: http://github.com/peterbe/django-fancy-cache
Author: Peter Bengtsson
Author-email: mail@peterbe.com
License: BSD
Platform: UNKNOWN
Classifier: Development Status :: 4 - Beta
Classifier: Intended Audience :: Developers
Classifier: License :: OSI Approved :: BSD License
Classifier: Operating System :: OS Independent
Classifier: Programming Language :: Python
Classifier: Programming Language :: Python :: 2
Classifier: Programming Language :: Python :: 2.6
Classifier: Programming Language :: Python :: 2.7
